oinker/__init__.py
oinker/_client.py
oinker/_config.py
oinker/_exceptions.py
oinker/_http.py
oinker/_sync.py
oinker/_sync_base.py
oinker/_types.py
oinker/cli/__init__.py
oinker/cli/_dns.py
oinker/cli/_dnssec.py
oinker/cli/_domains.py
oinker/cli/_main.py
oinker/cli/_pricing.py
oinker/cli/_ssl.py
oinker/cli/_utils.py
oinker/dns/__init__.py
oinker/dns/_api.py
oinker/dns/_records.py
oinker/dns/_sync.py
oinker/dnssec/__init__.py
oinker/dnssec/_api.py
oinker/dnssec/_sync.py
oinker/dnssec/_types.py
oinker/domains/__init__.py
oinker/domains/_api.py
oinker/domains/_sync.py
oinker/domains/_types.py
oinker/pricing/__init__.py
oinker/pricing/_api.py
oinker/pricing/_types.py
oinker/py.typed
oinker/ssl/__init__.py
oinker/ssl/_api.py
oinker/ssl/_sync.py
oinker/ssl/_types.py
oinker-0.1.2.dist-info/WHEEL
oinker-0.1.2.dist-info/entry_points.txt
oinker-0.1.2.dist-info/METADATA
oinker-0.1.2.dist-info/RECORD
