Metadata-Version: 2.4
Name: oinker
Version: 0.1.2
Summary: A delightfully Pythonic library for managing DNS at Porkbun
Keywords: dns,porkbun,api,domains
Author: Major Hayden
Author-email: Major Hayden <major@mhtx.net>
License-Expression: MIT
Classifier: Development Status :: 4 - Beta
Classifier: Intended Audience :: Developers
Classifier: License :: OSI Approved :: MIT License
Classifier: Programming Language :: Python :: 3.13
Classifier: Programming Language :: Python :: 3.14
Classifier: Topic :: Internet :: Name Service (DNS)
Classifier: Typing :: Typed
Requires-Dist: httpx>=0.28
Requires-Dist: typer>=0.15 ; extra == 'cli'
Requires-Dist: rich>=13 ; extra == 'cli'
Requires-Python: >=3.13
Project-URL: Homepage, https://github.com/major/oinker
Project-URL: Documentation, https://major.github.io/oinker
Project-URL: Repository, https://github.com/major/oinker
Provides-Extra: cli
